pyneMeas/__init__.py
pyneMeas/Instruments/Electrometer.py
pyneMeas/Instruments/Instrument.py
pyneMeas/Instruments/Keithley2000.py
pyneMeas/Instruments/Keithley2401.py
pyneMeas/Instruments/NoiseGenerator.py
pyneMeas/Instruments/SRS830.py
pyneMeas/Instruments/TimeMeas.py
pyneMeas/Instruments/USB6216In.py
pyneMeas/Instruments/USB6216Out.py
pyneMeas/Instruments/YokogawaGS200.py
pyneMeas/Instruments/__init__.py
pyneMeas/utility/GlobalMeasID.py
pyneMeas/utility/GlobalMeasIDBinary
pyneMeas/utility/SweepFunction.py
pyneMeas/utility/__init__.py
pyneMeas/utility/utils.py
pyneMeas-0.0.4.dist-info/LICENSE
pyneMeas-0.0.4.dist-info/METADATA
pyneMeas-0.0.4.dist-info/WHEEL
pyneMeas-0.0.4.dist-info/top_level.txt
pyneMeas-0.0.4.dist-info/RECORD
