Metadata-Version: 2.1
Name: pyneMeas
Version: 0.0.4
Summary: A simple Python 3 interface for controlling electronic measurement instruments and scripting measurement sweeps.
Home-page: https://github.com/JakobSeidl/pyneMeas
Author: Jakob Seidl
Author-email: jakob.seidl91@gmail.com
License: UNKNOWN
Platform: UNKNOWN
Classifier: Programming Language :: Python :: 3
Classifier: License :: OSI Approved :: MIT License
Classifier: Operating System :: OS Independent
Requires-Python: >=3.6
Requires-Dist: numpy
Requires-Dist: matplotlib
Requires-Dist: nidaqmx
Requires-Dist: pandas
Requires-Dist: scipy
Requires-Dist: pyvisa
